multiply/__init__.py
multiply/multiplication.py
Basic_ml_flow-0.1.dist-info/METADATA
Basic_ml_flow-0.1.dist-info/WHEEL
Basic_ml_flow-0.1.dist-info/top_level.txt
Basic_ml_flow-0.1.dist-info/RECORD
