Metadata-Version: 2.1
Name: Basic-ml-flow
Version: 0.1
Summary: Basic_ml_flow
Home-page: 
Author: Veena Rao
Author-email: veena.rao@hiro-microdatacenters.nl
License: MIT
